[
  {
    "2007": "1200",
    "2008": "1800",
    "2009": "2400",
    "2010": "2400",
    "2011": "2400",
    "2012": "2400",
    "2013": "2400",
    "2014": "2400",
    "2015": "2400",
    "2016": "2400",
    "2017": "",
    "2018": "1500",
    "2019": "1500",
    "2020": "2000",
    "2021": "2000",
    "2023": "1400",
    "20221": "2000",
    "20222": "1600",
    "department": "Eng-10"
  },
  {
    "2007": "1500",
    "2008": "2000",
    "2009": "2000",
    "2010": "2500",
    "2011": "2500",
    "2012": "2500",
    "2013": "2500",
    "2014": "2500",
    "2015": "2500",
    "2016": "2500",
    "2017": "",
    "2018": "1600",
    "2019": "1600",
    "2020": "2000",
    "2021": "2000",
    "2023": "Package",
    "20221": "2000",
    "20222": "1600",
    "department": "ELT-52"
  },
  {
    "2007": "1800",
    "2008": "1800",
    "2009": "1800",
    "2010": "2400",
    "2011": "2400",
    "2012": "2400",
    "2013": "2400",
    "2014": "2400",
    "2015": "2400",
    "2016": "2400",
    "2017": "",
    "2018": "1600",
    "2019": "1600",
    "2020": "2000",
    "2021": "2000",
    "2023": "1800",
    "20221": "2000",
    "20222": "2000",
    "department": "BBA-25"
  },
  {
    "2007": "0",
    "2008": "0",
    "2009": "0",
    "2010": "0",
    "2011": "0",
    "2012": "0",
    "2013": "0",
    "2014": "0",
    "2015": "0",
    "2016": "0",
    "2017": "0",
    "2018": "0",
    "2019": "0",
    "2020": "0",
    "2021": "0",
    "2023": "2000",
    "20221": "0",
    "20222": "0",
    "department": "BBA-26"
  },
  {
    "2007": "2000",
    "2008": "2000",
    "2009": "2000",
    "2010": "2500",
    "2011": "2500",
    "2012": "2500",
    "2013": "2500",
    "2014": "2500",
    "2015": "2500",
    "2016": "2500",
    "2017": "",
    "2018": "1600",
    "2019": "1600",
    "2020": "2000",
    "2021": "2000",
    "2023": "1600",
    "20221": "2000",
    "20222": "1600",
    "department": "MBA-64(1Y)"
  },
  {
    "2007": "2000",
    "2008": "2000",
    "2009": "2500",
    "2010": "2500",
    "2011": "2500",
    "2012": "2500",
    "2013": "0",
    "2014": "0",
    "2015": "0",
    "2016": "0",
    "2017": "",
    "2018": "1600",
    "2019": "1600",
    "2020": "2000",
    "2021": "2000",
    "2023": "1200",
    "20221": "2000",
    "20222": "1600",
    "department": "MBA-65(2Y)"
  },
  {
    "2007": "0",
    "2008": "0",
    "2009": "0",
    "2010": "0",
    "2011": "0",
    "2012": "0",
    "2013": "2500",
    "2014": "2500",
    "2015": "2500",
    "2016": "2500",
    "2017": "",
    "2018": "1600",
    "2019": "1600",
    "2020": "2000",
    "2021": "2000",
    "2023": "1600",
    "20221": "2000",
    "20222": "1600",
    "department": "EMBA-67(Exe)"
  },
  {
    "2007": "0",
    "2008": "0",
    "2009": "0",
    "2010": "0",
    "2011": "0",
    "2012": "0",
    "2013": "0",
    "2014": "0",
    "2015": "2400",
    "2016": "2400",
    "2017": "",
    "2018": "1600",
    "2019": "1600",
    "2020": "2000",
    "2021": "2000",
    "2023": "1600",
    "20221": "2000",
    "20222": "2000",
    "department": "CSE-38(D)"
  },
  {
    "2007": "0",
    "2008": "0",
    "2009": "0",
    "2010": "0",
    "2011": "0",
    "2012": "0",
    "2013": "0",
    "2014": "0",
    "2015": "2400",
    "2016": "2400",
    "2017": "",
    "2018": "1600",
    "2019": "1600",
    "2020": "2000",
    "2021": "2000",
    "2023": "0",
    "20221": "2000",
    "20222": "0",
    "department": "CSE-39(E)"
  },
  {
    "2007": "1800",
    "2008": "1800",
    "2009": "1800",
    "2010": "2400",
    "2011": "2400",
    "2012": "2400",
    "2013": "2400",
    "2014": "2400",
    "2015": "2400",
    "2016": "2400",
    "2017": "",
    "2018": "1600",
    "2019": "1600",
    "2020": "2000",
    "2021": "2000",
    "2023": "1200",
    "20221": "2000",
    "20222": "2000",
    "department": "EEE-40"
  },
  {
    "2007": "1800",
    "2008": "1800",
    "2009": "1800",
    "2010": "2400",
    "2011": "2400",
    "2012": "2400",
    "2013": "2400",
    "2014": "2400",
    "2015": "2400",
    "2016": "2400",
    "2017": "",
    "2018": "1600",
    "2019": "1600",
    "2020": "2000",
    "2021": "2000",
    "2023": "0",
    "20221": "2000",
    "20222": "0",
    "department": "EEE-41"
  },
  {
    "2007": "0",
    "2008": "0",
    "2009": "0",
    "2010": "0",
    "2011": "0",
    "2012": "0",
    "2013": "0",
    "2014": "0",
    "2015": "2400",
    "2016": "2400",
    "2017": "",
    "2018": "1600",
    "2019": "1600",
    "2020": "2000",
    "2021": "2000",
    "2023": "1600",
    "20221": "2000",
    "20222": "2000",
    "department": "EEE-44"
  },
  {
    "2007": "1800",
    "2008": "1800",
    "2009": "1800",
    "2010": "2400",
    "2011": "2400",
    "2012": "2400",
    "2013": "2400",
    "2014": "2400",
    "2015": "2400",
    "2016": "2400",
    "2017": "",
    "2018": "1600",
    "2019": "1600",
    "2020": "2000",
    "2021": "2000",
    "2023": "1200",
    "20221": "2000",
    "20222": "2000",
    "department": "Civil-45(D)"
  },
  {
    "2007": "1800",
    "2008": "1800",
    "2009": "1800",
    "2010": "2400",
    "2011": "2400",
    "2012": "2400",
    "2013": "2400",
    "2014": "2400",
    "2015": "2400",
    "2016": "2400",
    "2017": "",
    "2018": "1600",
    "2019": "1600",
    "2020": "2000",
    "2021": "2000",
    "2023": "1600",
    "20221": "2000",
    "20222": "2000",
    "department": "Civil-46(E)"
  },
  {
    "2007": "0",
    "2008": "0",
    "2009": "0",
    "2010": "0",
    "2011": "0",
    "2012": "0",
    "2013": "0",
    "2014": "0",
    "2015": "2400",
    "2016": "2400",
    "2017": "",
    "2018": "1600",
    "2019": "1600",
    "2020": "2000",
    "2021": "2000",
    "2023": "2000",
    "20221": "2000",
    "20222": "2000",
    "department": "Civil-47(W)"
  },
  {
    "2007": "0",
    "2008": "0",
    "2009": "0",
    "2010": "0",
    "2011": "0",
    "2012": "0",
    "2013": "0",
    "2014": "0",
    "2015": "",
    "2016": "",
    "2017": "",
    "2018": "1500",
    "2019": "1500",
    "2020": "2000",
    "2021": "2000",
    "2023": "800",
    "20221": "2000",
    "20222": "800",
    "department": "BSS in Eco"
  }
]
